PyQtPaint/__init__.py
PyQtPaint/app.py
PyQtPaint/form.py
PyQtPaint/objects.py
pyqtpaint-0.2.1.dist-info/licenses/LICENSE
pyqtpaint-0.2.1.dist-info/METADATA
pyqtpaint-0.2.1.dist-info/WHEEL
pyqtpaint-0.2.1.dist-info/top_level.txt
pyqtpaint-0.2.1.dist-info/RECORD
