Metadata-Version: 2.4
Name: PyQtPaint
Version: 0.2.1
Summary: A library the uses PyQt5 for setting up apps with a window to programatically draw in.
Author-email: WafflerThe <wafflerthe@gmail.com>
License-Expression: MIT
Project-URL: Homepage, https://github.com/WafflerThe/PyQtPaint
Classifier: Programming Language :: Python :: 3
Classifier: Operating System :: OS Independent
Requires-Python: >=3.13
License-File: LICENSE
Requires-Dist: PyQt5>=5.15.11
Dynamic: license-file
